README.rst
setup.py
mvmv/__init__.py
mvmv/cli.py
mvmv/daemon.py
mvmv/mvmv.py
mvmv/mvmvd.py
mvmv/mvtest.py
mvmv/parse.py
mvmv/test.py
mvmv.egg-info/PKG-INFO
mvmv.egg-info/SOURCES.txt
mvmv.egg-info/dependency_links.txt
mvmv.egg-info/entry_points.txt
mvmv.egg-info/requires.txt
mvmv.egg-info/top_level.txt
test/test.py