Metadata-Version: 1.0
Name: mvmv
Version: 1.1
Summary: Movie Mover - move your movies where they belong.
Home-page: https://github.com/wmak/mvmv
Author: William Mak, Prajjwal Bhandari, Matt Olan
Author-email: william@wmak.io, pbhandari@pbhandari.ca, hello@olanmatt.com
License: MIT
Platform: UNKNOWN
